tzconv/__init__.py
tzconv/test_tzconv.py
tzconv-1.3.1.dist-info/METADATA
tzconv-1.3.1.dist-info/WHEEL
tzconv-1.3.1.dist-info/entry_points.txt
tzconv-1.3.1.dist-info/top_level.txt
tzconv-1.3.1.dist-info/RECORD
