Metadata-Version: 2.1
Name: tzconv
Version: 1.3.1
Summary: command-line tool to convert a date and time to several time zones at once
Home-page: https://codeberg.org/gnyeki/tzconv
Author: Gabor Nyeki
Requires-Dist: click
